<resources>
    <color name="chatPageMainBackground">#202B4F</color>
    <color name="defaultChatItemBackground">#1F2747</color>
    <color name="gradientChatMessageItem">#F68D3D</color>
    <color name="loginFormBackground">#55D4AB</color>
    <color name="topItemLoginFormBackground">#00BD8F</color>
    <color name="tabBarBackground">#331F5E</color>


    <color name="gradientColor1">#dd5d3e</color>
    <color name="gradientColor2">#ec603e</color>
    <color name="gradientColor3">#2d3271</color>
    <color name="gradientColor4">#212e67</color>

</resources>